docs/DND.png
docs/abr.png
docs/cal-error.png
docs/interface.png
ncrar_abr/__init__.py
ncrar_abr/abr-icon.ico
ncrar_abr/abr-icon.png
ncrar_abr/abrpanel.py
ncrar_abr/app.py
ncrar_abr/compare.py
ncrar_abr/compare_window.enaml
ncrar_abr/datatype.py
ncrar_abr/launch_window.enaml
ncrar_abr/main_window.enaml
ncrar_abr/peakdetect.py
ncrar_abr/presenter.py
ncrar_abr/version.py
ncrar_abr/data/ABR-52-3
ncrar_abr/data/CAP-139-5
ncrar_abr/data/CAP-139-5-16.0kHz-Brad-analyzed.txt
ncrar_abr/data/CAP-139-5-16.0kHz-analyzed.txt
ncrar_abr/parsers/NCRAR.py
ncrar_abr/parsers/__init__.py
ncrar_abr-2024.2.14.dist-info/LICENSE.txt
ncrar_abr-2024.2.14.dist-info/METADATA
ncrar_abr-2024.2.14.dist-info/WHEEL
ncrar_abr-2024.2.14.dist-info/entry_points.txt
ncrar_abr-2024.2.14.dist-info/top_level.txt
ncrar_abr-2024.2.14.dist-info/RECORD
