Metadata-Version: 2.1
Name: ncrar-abr
Version: 2024.2.14
Summary: Evoked potential analysis software
Author-email: Brad Buran <bburan@alum.mit.edu>, Brad Buran <buran@ohsu.edu>, Brad Buran <bradley.buran@va.gov>
Maintainer-email: Brad Buran <bburan@alum.mit.edu>, Brad Buran <buran@ohsu.edu>, Brad Buran <bradley.buran@va.gov>
License: BSD 3-Clause License
Project-URL: homepage, https://github.com/NCRAR/ncrar-abr
Project-URL: documentation, https://github.com/NCRAR/ncrar-abr
Project-URL: repository, https://github.com/NCRAR/ncrar-abr
Classifier: Operating System :: OS Independent
Classifier: Programming Language :: Python :: 3
Classifier: License :: OSI Approved :: BSD License
Requires-Python: >=3.9
License-File: LICENSE.txt
Requires-Dist: atom
Requires-Dist: enaml[qt6-pyside]
Requires-Dist: numpy
Requires-Dist: scipy
Requires-Dist: pandas
Requires-Dist: matplotlib
Requires-Dist: openpyxl
